readme_copier/__init__.py
readme_copier/cheatsheet.py
readme_copier/cli.py
readme_copier/copier.py
readme_copier/quiz.7z
security_run_off-0.1.3.dist-info/licenses/LICENSE
security_run_off-0.1.3.dist-info/METADATA
security_run_off-0.1.3.dist-info/WHEEL
security_run_off-0.1.3.dist-info/entry_points.txt
security_run_off-0.1.3.dist-info/top_level.txt
security_run_off-0.1.3.dist-info/RECORD
