Metadata-Version: 2.4
Name: security-run-off
Version: 0.1.3
Summary: A utility package to copy README files to project folders
Home-page: https://github.com/kvsh443/security-run-off
Author: kvsh443
Author-email: kvsh443 <poc@kvsh.xyz>
Project-URL: Homepage, https://github.com/kvsh443/security-run-off
Project-URL: Bug Tracker, https://github.com/kvsh443/security-run-off/issues
Classifier: Programming Language :: Python :: 3
Classifier: Programming Language :: Python :: 3.8
Classifier: Programming Language :: Python :: 3.9
Classifier: Programming Language :: Python :: 3.10
Classifier: Programming Language :: Python :: 3.11
Classifier: Programming Language :: Python :: 3.12
Classifier: License :: OSI Approved :: MIT License
Classifier: Operating System :: OS Independent
Requires-Python: >=3.8
License-File: LICENSE
Requires-Dist: click>=8.0.0
Dynamic: author
Dynamic: home-page
Dynamic: license-file
Dynamic: requires-python
